dlt_metabase_source/__init__.py
dlt_metabase_source/_helpers.py
dlt_metabase_source/example_schemas/example_schema_unedited.yml
dlt_metabase_source/example_schemas/example_schema_with_less_unnesting.yml
dlt_metabase_source/extract_sample_data.py
dlt_metabase_source/extract_schema.py
dlt_metabase_source/metabase_source.py
dlt_metabase_source/mock_source.py
dlt_metabase_source/run_pipeline.py
dlt_metabase_source/sample_data/activity.jsonl
dlt_metabase_source/sample_data/cards.jsonl
dlt_metabase_source/sample_data/cleaner_util.py
dlt_metabase_source/sample_data/collections.jsonl
dlt_metabase_source/sample_data/dashboards.jsonl
dlt_metabase_source/sample_data/databases.jsonl
dlt_metabase_source/sample_data/fields.jsonl
dlt_metabase_source/sample_data/logs.jsonl
dlt_metabase_source/sample_data/metrics.jsonl
dlt_metabase_source/sample_data/pulses.jsonl
dlt_metabase_source/sample_data/segments.jsonl
dlt_metabase_source/sample_data/stats.jsonl
dlt_metabase_source/sample_data/tables.jsonl
dlt_metabase_source/sample_data/users.jsonl
dlt_metabase_source/schema.yml
dlt_metabase_source-0.0.26.dist-info/LICENSE
dlt_metabase_source-0.0.26.dist-info/WHEEL
dlt_metabase_source-0.0.26.dist-info/METADATA
dlt_metabase_source-0.0.26.dist-info/RECORD
