Metadata-Version: 2.1
Name: dlt-metabase-source
Version: 0.0.26
Summary: 
License: apache
Author: Adrian Brudaru
Author-email: adrian@scalevector.ai
Requires-Python: >=3.8,<4.0
Classifier: License :: Other/Proprietary License
Classifier: Programming Language :: Python :: 3
Classifier: Programming Language :: Python :: 3.10
Classifier: Programming Language :: Python :: 3.8
Classifier: Programming Language :: Python :: 3.9
Requires-Dist: google-cloud-bigquery
Requires-Dist: psycopg2-binary
Requires-Dist: python-dlt
